{
  "Baseline": {
    "experiment": "baseline_traditional",
    "final_loss": 3.2581520080566406,
    "history": [
      {
        "step": 1,
        "loss": 5.714120864868164,
        "time": 27.220790147781372,
        "samples_per_sec": 1.8368313237253786
      },
      {
        "step": 2,
        "loss": 3.823509693145752,
        "time": 25.44962215423584,
        "samples_per_sec": 1.9646657108297378
      },
      {
        "step": 3,
        "loss": 4.521334648132324,
        "time": 23.60331082344055,
        "samples_per_sec": 2.1183468867572928
      },
      {
        "step": 4,
        "loss": 3.420976161956787,
        "time": 25.594907999038696,
        "samples_per_sec": 1.9535135661311196
      },
      {
        "step": 5,
        "loss": 3.2581520080566406,
        "time": 25.56917095184326,
        "samples_per_sec": 1.9554799056320415
      }
    ],
    "wall_time": 127.65763187408447
  },
  "SwarmMomentum": {
    "experiment": "swarm_momentum",
    "final_loss": 2.8512556850910187,
    "avg_consensus": 0.9463213662306468,
    "history": [
      {
        "step": 1,
        "loss": 5.6982874274253845,
        "consensus": 0.9731175303459167,
        "effective_lr": 0.002932793825864792,
        "lr_multiplier": 2.932793825864792
      },
      {
        "step": 2,
        "loss": 3.620843827724457,
        "consensus": 0.9927038848400116,
        "effective_lr": 0.002981759712100029,
        "lr_multiplier": 2.981759712100029
      },
      {
        "step": 3,
        "loss": 4.966190338134766,
        "consensus": 0.9981437027454376,
        "effective_lr": 0.002995359256863594,
        "lr_multiplier": 2.995359256863594
      },
      {
        "step": 4,
        "loss": 4.302300870418549,
        "consensus": 0.9977350234985352,
        "effective_lr": 0.002994337558746338,
        "lr_multiplier": 2.994337558746338
      },
      {
        "step": 5,
        "loss": 3.7766397893428802,
        "consensus": 0.9812957644462585,
        "effective_lr": 0.0029532394111156466,
        "lr_multiplier": 2.9532394111156464
      },
      {
        "step": 6,
        "loss": 3.435867816209793,
        "consensus": 0.9718929827213287,
        "effective_lr": 0.0029297324568033217,
        "lr_multiplier": 2.929732456803322
      },
      {
        "step": 7,
        "loss": 3.3298602998256683,
        "consensus": 0.9611403942108154,
        "effective_lr": 0.0029028509855270387,
        "lr_multiplier": 2.9028509855270386
      },
      {
        "step": 8,
        "loss": 3.2815340161323547,
        "consensus": 0.9638174474239349,
        "effective_lr": 0.0029095436185598376,
        "lr_multiplier": 2.9095436185598373
      },
      {
        "step": 9,
        "loss": 3.1718868613243103,
        "consensus": 0.96287402510643,
        "effective_lr": 0.0029071850627660754,
        "lr_multiplier": 2.907185062766075
      },
      {
        "step": 10,
        "loss": 3.012328654527664,
        "consensus": 0.9214936792850494,
        "effective_lr": 0.002803734198212624,
        "lr_multiplier": 2.8037341982126236
      },
      {
        "step": 11,
        "loss": 2.9862404465675354,
        "consensus": 0.9588372111320496,
        "effective_lr": 0.002897093027830124,
        "lr_multiplier": 2.897093027830124
      },
      {
        "step": 12,
        "loss": 2.9155279994010925,
        "consensus": 0.8729354739189148,
        "effective_lr": 0.002682338684797287,
        "lr_multiplier": 2.682338684797287
      },
      {
        "step": 13,
        "loss": 2.902104616165161,
        "consensus": 0.8790040910243988,
        "effective_lr": 0.002697510227560997,
        "lr_multiplier": 2.697510227560997
      },
      {
        "step": 14,
        "loss": 2.8942757546901703,
        "consensus": 0.8988755643367767,
        "effective_lr": 0.002747188910841942,
        "lr_multiplier": 2.747188910841942
      },
      {
        "step": 15,
        "loss": 2.8512556850910187,
        "consensus": 0.8609537184238434,
        "effective_lr": 0.0026523842960596085,
        "lr_multiplier": 2.6523842960596085
      }
    ],
    "wall_time": 111.44139409065247
  }
}